deltric/__init__.py
deltric/deltric.py
deltric/utils.py
deltric-0.1.0.dist-info/licenses/LICENSE
deltric-0.1.0.dist-info/METADATA
deltric-0.1.0.dist-info/WHEEL
deltric-0.1.0.dist-info/top_level.txt
deltric-0.1.0.dist-info/RECORD
